llq/__init__.py
llq/demo.py
llq/that.py
llq/util/__init__.py
llq/util/data/__init__.py
llq/util/data/book.py
llq/util/data/fakeData.py
llq/util/data/slide_window.py
llq/util/devices/GPU.py
llq/util/devices/__init__.py
llq/util/network/__init__.py
llq/util/network/baiduTop.py
llq/util/network/wifi.py
shnu_llq_tools-1.0.3.dist-info/METADATA
shnu_llq_tools-1.0.3.dist-info/WHEEL
shnu_llq_tools-1.0.3.dist-info/top_level.txt
shnu_llq_tools-1.0.3.dist-info/RECORD
